[
  {
    "title": "Simple Tasks",
    "slug": "simple-tasks",
    "demo": null,
    "tutorial": null,
    "repository": "fredmaiaarantes/simpletasks",
    "repositoryUrl": "https://github.com/fredmaiaarantes/simpletasks",
    "isInternal": false,
    "internalPath": null,
    "why": "A task management app showcasing form handling, user accounts, and a polished component-based UI",
    "stack": [
      "Meteor",
      "Rspack",
      "Chakra UI",
      "React",
      "Formik",
      "MongoDB"
    ],
    "lastUpdatedAt": "Feb/12/2026",
    "meteorVersion": "3.4"
  },
  {
    "title": "Task Manager",
    "slug": "task-manager",
    "demo": null,
    "tutorial": null,
    "repository": "meteor/examples",
    "repositoryUrl": "https://github.com/meteor/examples/tree/main/task-manager",
    "isInternal": true,
    "internalPath": "task-manager",
    "why": "Task management with CRUD, status workflows, priority filtering, real-time dashboard, and type-safe RPC",
    "stack": [
      "Meteor",
      "Rspack",
      "React",
      "Meteor-RPC",
      "shadcn/ui",
      "Tailwind CSS",
      "React Query",
      "Zod",
      "Mocha",
      "Biome",
      "Playwright"
    ],
    "lastUpdatedAt": "Mar/18/2026",
    "meteorVersion": "3.4.1-beta.1"
  },
  {
    "title": "Tic-Tac-Toe",
    "slug": "tic-tac-toe",
    "demo": null,
    "tutorial": null,
    "repository": "meteor/examples",
    "repositoryUrl": "https://github.com/meteor/examples/tree/main/tic-tac-toe",
    "isInternal": true,
    "internalPath": "tic-tac-toe",
    "why": "Real-time multiplayer game with room-based matchmaking and live state sync via pub/sub",
    "stack": [
      "Meteor",
      "Rspack",
      "React",
      "MUI (Material UI)",
      "Mocha",
      "oxlint",
      "Playwright"
    ],
    "lastUpdatedAt": "Mar/17/2026",
    "meteorVersion": "3.4.1-beta.1"
  },
  {
    "title": "Simple Blog",
    "slug": "simple-blog",
    "demo": null,
    "tutorial": null,
    "repository": "dupontbertrand/meteor-blog",
    "repositoryUrl": "https://github.com/dupontbertrand/meteor-blog",
    "isInternal": false,
    "internalPath": null,
    "why": "Mini blog with role-based access control, post/comment management, email notifications, and dev-mode mail preview",
    "stack": [
      "Meteor",
      "Rspack",
      "Blaze 3",
      "Bootstrap 5",
      "Flow Router",
      "MJML"
    ],
    "lastUpdatedAt": "Mar/24/2026",
    "meteorVersion": "3.4"
  },
  {
    "title": "Notes Offline",
    "slug": "notes-offline",
    "demo": null,
    "tutorial": null,
    "repository": "meteor/examples",
    "repositoryUrl": "https://github.com/meteor/examples/tree/main/notes-offline",
    "isInternal": true,
    "internalPath": "notes-offline",
    "why": "Offline-first PWA notes app with auto-save, markdown, search, tagging, pinning, trash/recovery, import/export, and cross-tab sync",
    "stack": [
      "Meteor",
      "Rspack",
      "React",
      "Mantine UI",
      "jam:offline",
      "jam:method",
      "jam:pub-sub",
      "jam:soft-delete",
      "Zod",
      "Workbox",
      "Mocha",
      "ESLint",
      "Prettier",
      "Playwright"
    ],
    "lastUpdatedAt": "Mar/18/2026",
    "meteorVersion": "3.4.1-beta.1"
  },
  {
    "title": "Complex Todos (Svelte)",
    "slug": "complex-todos-svelte",
    "demo": null,
    "tutorial": null,
    "repository": "meteor/examples",
    "repositoryUrl": "https://github.com/meteor/examples/tree/main/complex-todos-svelte",
    "isInternal": true,
    "internalPath": "complex-todos-svelte",
    "why": "Production-grade todo app with modular monolith architecture, rate limiting, caching, migrations, scheduled jobs, and E2E tests",
    "stack": [
      "Meteor",
      "Rspack",
      "Svelte 5",
      "Skeleton UI",
      "Tailwind CSS v4",
      "jam:method",
      "Zod",
      "oxlint",
      "Cypress",
      "Mocha",
      "MongoDB"
    ],
    "lastUpdatedAt": "Mar/19/2026",
    "meteorVersion": "3.4.1-beta.1"
  },
  {
    "title": "Welcome Meteor Cordova",
    "slug": "welcome-meteor-cordova",
    "demo": null,
    "tutorial": null,
    "repository": "CloudByGalaxy/welcome-meteor-cordova",
    "repositoryUrl": "https://github.com/CloudByGalaxy/welcome-meteor-cordova",
    "isInternal": false,
    "internalPath": null,
    "why": "To show how to set up a Meteor app with Cordova for mobile usage",
    "stack": [
      "Meteor",
      "Cordova"
    ],
    "lastUpdatedAt": null,
    "meteorVersion": "3.4.1-beta.1"
  },
  {
    "title": "NFT Marketplace",
    "slug": "nft-marketplace",
    "demo": null,
    "tutorial": null,
    "repository": "meteor/examples",
    "repositoryUrl": "https://github.com/meteor/examples/tree/main/nft-marketplace",
    "isInternal": true,
    "internalPath": "nft-marketplace",
    "why": "Decentralized NFT marketplace for minting, listing, and buying NFTs with wallet auth and on-chain transactions",
    "stack": [
      "Meteor",
      "Rspack",
      "React",
      "TailwindCSS",
      "Polygon",
      "Solidity",
      "Hardhat",
      "Ethers.js",
      "and IPFS"
    ],
    "lastUpdatedAt": "Mar/14/2026",
    "meteorVersion": "3.4.1-beta.1"
  }
]
